assetsstore/__init__.py
assetsstore/assets/__init__.py
assetsstore/assets/assets.py
assetsstore/assets/azr/__init__.py
assetsstore/assets/azr/azure_files.py
assetsstore/assets/local/__init__.py
assetsstore/assets/local/local_files.py
assetsstore/assets/minio/__init__.py
assetsstore/assets/minio/minio.py
assetsstore/assets/minio/progress.py
assetsstore/assets/s3/__init__.py
assetsstore/assets/s3/async_s3_files.py
assetsstore/assets/s3/s3_files.py
assetsstore/assets/server/__init__.py
assetsstore/assets/server/server_files.py
assetsstore/tests/__init__.py
assetsstore/tests/test_async_s3.py
assetsstore/tests/test_local.py
assetsstore/tests/test_minio.py
assetsstore/tests/fixtures/test.txt
assetsstore/tests/fixtures/test_folder/test2.txt
assetsstore-1.8.8.dist-info/licenses/LICENSE
assetsstore-1.8.8.dist-info/WHEEL
assetsstore-1.8.8.dist-info/METADATA
assetsstore-1.8.8.dist-info/RECORD
