Metadata-Version: 2.4
Name: AssetsStore
Version: 1.8.8
Summary: Python package for managing file upload/download via selected file system.
Author-email: Nebojsa Mrkic <mrkic.nebojsa@gmail.com>
Classifier: License :: OSI Approved :: Apache Software License
License-File: LICENSE
Requires-Dist: requests>=2.25.1
Requires-Dist: urllib3>=1.26.20
Requires-Dist: aioboto3>=15.0.0 ; extra == "async-s3"
Requires-Dist: azure-storage-blob==2.1.0 ; extra == "azure"
Requires-Dist: minio>=7.1.13 ; extra == "minio"
Requires-Dist: boto3>=1.38.0 ; extra == "s3"
Requires-Dist: paramiko>=3.2.0 ; extra == "server"
Requires-Dist: requests ; extra == "tests"
Requires-Dist: pre-commit ; extra == "tests"
Requires-Dist: pytest-mock ; extra == "tests"
Requires-Dist: pytest-asyncio ; extra == "tests"
Requires-Dist: pytest ; extra == "tests"
Project-URL: Home, https://github.com/nmrkic/AssetsStore
Provides-Extra: async-s3
Provides-Extra: azure
Provides-Extra: minio
Provides-Extra: s3
Provides-Extra: server
Provides-Extra: tests
